firepydaq/__init__.py
firepydaq/acquisition/__init__.py
firepydaq/acquisition/acquisition.py
firepydaq/acquisition/device.py
firepydaq/acquisition/DeviceNameDialog.py
firepydaq/acquisition/display_data_tab.py
firepydaq/acquisition/exception_list.py
firepydaq/acquisition/LoadSettingsDialog.py
firepydaq/acquisition/MainMenu.py
firepydaq/acquisition/NIAOtab.py
firepydaq/acquisition/NotificationPanel.py
firepydaq/acquisition/RemoveDeviceDialog.py
firepydaq/acquisition/SaveSettingsDialog.py
firepydaq/acquisition/schema.py
firepydaq/api/__init__.py
firepydaq/api/EchoAlicat.py
firepydaq/api/EchoNIDAQTask.py
firepydaq/api/EchoThorLabsCLD101X.py
firepydaq/assets/FIREpyDAQDark.png
firepydaq/assets/FIREpyDAQLight.png
firepydaq/assets/popup_dark.css
firepydaq/assets/popup_light.css
firepydaq/assets/styles_dark.css
firepydaq/assets/styles_light.css
firepydaq/dashboard/__init__.py
firepydaq/dashboard/app.py
firepydaq/dashboard/assets/icons8-graph-50.png
firepydaq/dashboard/assets/icons8-moon-24.png
firepydaq/dashboard/assets/icons8-pause-48.png
firepydaq/dashboard/assets/icons8-play-50.png
firepydaq/dashboard/assets/icons8-sun-24.png
firepydaq/dashboard/assets/scripts.js
firepydaq/dashboard/assets/styles.css
firepydaq/FIREpyDAQ_Acquisition.py
firepydaq/utilities/__init__.py
firepydaq/utilities/DAQUtils.py
firepydaq/utilities/ErrorUtils.py
firepydaq/utilities/NISYSCheck.py
firepydaq/utilities/PostProcessing.py
firepydaq-0.1.1.dist-info/AUTHORS.md
firepydaq-0.1.1.dist-info/LICENSE
firepydaq-0.1.1.dist-info/METADATA
firepydaq-0.1.1.dist-info/WHEEL
firepydaq-0.1.1.dist-info/RECORD
