Metadata-Version: 2.1
Name: firepydaq
Version: 0.1.1
Summary: Facilitated Interface for Recording Experiments (FIRE), a python-based Data Acquisition package for nidaqmx, Alicat, and ThorlabsCLD101X devices.
License: GNU General Public v3
Author: Dushyant Chaudhari
Author-email: dushyant.chaudhari@ul.org
Requires-Python: >=3.9,<3.13
Classifier: License :: Other/Proprietary License
Classifier: Programming Language :: Python :: 3
Classifier: Programming Language :: Python :: 3.9
Classifier: Programming Language :: Python :: 3.10
Classifier: Programming Language :: Python :: 3.11
Classifier: Programming Language :: Python :: 3.12
Requires-Dist: PySide6 (>=6.7.2,<7.0.0)
Requires-Dist: PyVISA (>=1.14.1,<2.0.0)
Requires-Dist: alicat (>=0.6.2,<0.7.0)
Requires-Dist: dash (>=2.17.1,<3.0.0)
Requires-Dist: dash-auth (>=2.3.0,<3.0.0)
Requires-Dist: dash-bootstrap-components (>=1.6.0,<2.0.0)
Requires-Dist: dash-daq (>=0.5.0,<0.6.0)
Requires-Dist: jsonschema (>=4.23.0,<5.0.0)
Requires-Dist: matplotlib (>=3.7.0,<4.0.0)
Requires-Dist: nidaqmx (>=1.0.0,<2.0.0)
Requires-Dist: numpy (>=1.26.0,<2.0.0)
Requires-Dist: pandas (>=2.2.2,<3.0.0)
Requires-Dist: plotly (>=5.22.0,<6.0.0)
Requires-Dist: polars (==1.5.0)
Requires-Dist: pyarrow (>=14.0.2)
Requires-Dist: pyqtgraph (>=0.13.7,<0.14.0)
Requires-Dist: pyserial (>=3.5,<4.0)
Requires-Dist: setuptools (>=72.1.0,<73.0.0)
